Metadata-Version: 2.1
Name: nonebot-plugin-backup
Version: 1.0.5
Summary: A plugin based on NoneBot2 to backup files in qq group.
Home-page: https://github.com/Yuelioi/nonebot-plugin-backup
Author: Yueli
Author-email: yuelioi1210@gmail.com
License: UNKNOWN
Project-URL: Bug Tracker, https://github.com/Yuelioi/nonebot-plugin-backup/issues
Platform: UNKNOWN
Classifier: Programming Language :: Python :: 3
Classifier: License :: OSI Approved :: GNU General Public License v3 (GPLv3)
Classifier: Operating System :: OS Independent
Requires-Python: >=3.7
Requires-Dist: nonebot2 (>=2.0.0b2)
Requires-Dist: nonebot-adapter-onebot (>=2.0.0b1)
Requires-Dist: requests (>=2.28.1)
